MANIFEST.in
README.rst
TITLE.txt
lh-agpl3-LICENSE.txt
setup.py
./bin/gcipher
unisos2/__init__.py
unisos2.gcipher.egg-info/PKG-INFO
unisos2.gcipher.egg-info/SOURCES.txt
unisos2.gcipher.egg-info/dependency_links.txt
unisos2.gcipher.egg-info/namespace_packages.txt
unisos2.gcipher.egg-info/not-zip-safe
unisos2.gcipher.egg-info/top_level.txt
unisos2/gcipher/AutomaticClass.py
unisos2/gcipher/Const.py
unisos2/gcipher/GtkAttributesFacade.py
unisos2/gcipher/LibGladeApplication.py
unisos2/gcipher/MainCLI.py
unisos2/gcipher/MainGUI.py
unisos2/gcipher/Proxy.py
unisos2/gcipher/__init__.py
unisos2/gcipher/cipher/Caesar.py
unisos2/gcipher/cipher/CharacterCipher.py
unisos2/gcipher/cipher/Gie.py
unisos2/gcipher/cipher/KeyedCipher.py
unisos2/gcipher/cipher/Rot.py
unisos2/gcipher/cipher/Tools.py
unisos2/gcipher/cipher/Vigenere.py
unisos2/gcipher/cipher/__init__.py
unisos2/gcipher/ciphergui/Caesar.py
unisos2/gcipher/ciphergui/CipherGUIList.py
unisos2/gcipher/ciphergui/Gie.py
unisos2/gcipher/ciphergui/KeyDialog.py
unisos2/gcipher/ciphergui/Rot.py
unisos2/gcipher/ciphergui/Vigenere.py
unisos2/gcipher/ciphergui/__init__.py